HTTP/1.1 200 OK
Server: Apache-Coyote/1.1
Set-Cookie: JSESSIONID=91CE090E7FB01429118DFC8FDD75DF4F; Path=/main2
Content-Type: text/xml;charset=UTF-8
Transfer-Encoding: chunked
Date: Thu, 20 Nov 2008 09:26:24 GMT

252
<?xml version='1.0' encoding='UTF-8'?>
   <soapenv:Envelope xmlns:soapenv="http://schemas.xmlsoap.org/soap/envelope/">
      <soapenv:Body>
         <ns1:queryResponse xmlns:ns1="http://api.zuora.com/">
            <ns1:result>
               <ns1:done>true</ns1:done>
               <ns1:queryLocator xmlns:xsi="http://www.w3.org/2001/XMLSchema-instance" xsi:nil="1" />
               <ns1:records xmlns:ns2="http://object.api.zuora.com/" xmlns:xsi="http://www.w3.org/2001/XMLSchema-instance" xsi:type="ns2:RatePlanCharge">
                  <ns2:Id>402882eb1db8f6b6011db938bfee009a</ns2:Id>
                  <ns2:Name>test_recuring</ns2:Name>
               </ns1:records>
               <ns1:size>1</ns1:size>
            </ns1:result>
         </ns1:queryResponse>
22

      </soapenv:Body>
   </soapenv:Envelope>0

